fontline/__init__.py
fontline/app.py
fontline/commands.py
fontline/metrics.py
fontline/settings.py
fontline/utilities.py
font_line-3.1.4.dist-info/LICENSE.md
font_line-3.1.4.dist-info/METADATA
font_line-3.1.4.dist-info/WHEEL
font_line-3.1.4.dist-info/entry_points.txt
font_line-3.1.4.dist-info/top_level.txt
font_line-3.1.4.dist-info/RECORD
