Metadata-Version: 2.1
Name: font-line
Version: 3.1.4
Summary: A font vertical metrics reporting and line spacing adjustment tool
Home-page: https://github.com/source-foundry/font-line
Author: Christopher Simpkins
Author-email: chris@sourcefoundry.org
License: MIT license
Keywords: font,typeface,fonts,spacing,line spacing,spaces,vertical metrics,metrics,type
Platform: any
Classifier: Development Status :: 5 - Production/Stable
Classifier: Natural Language :: English
Classifier: License :: OSI Approved :: MIT License
Classifier: Operating System :: OS Independent
Classifier: Programming Language :: Python
Classifier: Programming Language :: Python :: 3
Classifier: Programming Language :: Python :: 3.6
Classifier: Programming Language :: Python :: 3.7
Classifier: Programming Language :: Python :: 3.8
Classifier: Programming Language :: Python :: 3.9
Classifier: Topic :: Software Development :: Libraries :: Python Modules
Requires-Dist: commandlines
Requires-Dist: standardstreams
Requires-Dist: fontTools
